funcnodes_basic/__init__.py
funcnodes_basic/dataclass.py
funcnodes_basic/dicts.py
funcnodes_basic/input.py
funcnodes_basic/lists.py
funcnodes_basic/logic.py
funcnodes_basic/math_nodes.py
funcnodes_basic/pyobjects.py
funcnodes_basic/strings.py
funcnodes_basic-1.0.0.dist-info/licenses/LICENSE
funcnodes_basic-1.0.0.dist-info/METADATA
funcnodes_basic-1.0.0.dist-info/WHEEL
funcnodes_basic-1.0.0.dist-info/entry_points.txt
funcnodes_basic-1.0.0.dist-info/top_level.txt
funcnodes_basic-1.0.0.dist-info/RECORD
