Metadata-Version: 2.4
Name: funcnodes-basic
Version: 1.0.0
Summary: Basic functionalities for funcnodes
Author-email: Julian Kimmig <julian.kimmig@linkdlab.de>
License: AGPL-3.0
Project-URL: homepage, https://github.com/Linkdlab/funcnodes_basic
Project-URL: source, https://github.com/Linkdlab/funcnodes_basic
Project-URL: tracker, https://github.com/Linkdlab/funcnodes_basic/issues
Project-URL: download, https://pypi.org/project/funcnodes-basic/#files
Classifier: License :: OSI Approved :: GNU Affero General Public License v3 or later (AGPLv3+)
Requires-Python: >=3.11
License-File: LICENSE
Requires-Dist: funcnodes-core>=1.0.5
Requires-Dist: funcnodes
Dynamic: license-file
